hue_plus/__init__.py
hue_plus/hue.py
hue_plus/hue_gui.py
hue_plus/hue_ui.py
hue_plus/picker.py
hue_plus/previous.py
hue_plus/webcolors.py
hue_plus/things/previous.p
hue_plus-1.4.5.dist-info/DESCRIPTION.rst
hue_plus-1.4.5.dist-info/METADATA
hue_plus-1.4.5.dist-info/RECORD
hue_plus-1.4.5.dist-info/WHEEL
hue_plus-1.4.5.dist-info/entry_points.txt
hue_plus-1.4.5.dist-info/metadata.json
hue_plus-1.4.5.dist-info/top_level.txt
