Metadata-Version: 2.0
Name: hue-plus
Version: 1.4.5
Summary: A utility to control the NZXT Hue+ in Linux
Home-page: http://github.com/kusti8/hue-plus
Author: Gustav Hansen
Author-email: kusti8@gmail.com
License: GPL3
Keywords: nzxt hue hue-plus hue_plus hue+
Platform: UNKNOWN
Classifier: Development Status :: 5 - Production/Stable
Classifier: License :: OSI Approved :: GNU General Public License v3 or later (GPLv3+)
Classifier: Programming Language :: Python :: 3 :: Only
Classifier: Operating System :: POSIX :: Linux
Requires-Dist: appdirs
Requires-Dist: pyaudio
Requires-Dist: pyqt5
Requires-Dist: pyserial
